tghandler.py
tghandler-1.1.dist-info/METADATA
tghandler-1.1.dist-info/WHEEL
tghandler-1.1.dist-info/top_level.txt
tghandler-1.1.dist-info/RECORD
