Metadata-Version: 2.1
Name: tghandler
Version: 1.1
Summary: Package for telegram bot - @Django_Error_Bot
Home-page: UNKNOWN
Author: Dmitriy Shvidkiy
License: UNKNOWN
Platform: UNKNOWN
Classifier: Programming Language :: Python :: 3
Classifier: License :: OSI Approved :: MIT License
Classifier: Operating System :: OS Independent
Requires-Python: >=3.6
Requires-Dist: requests
